{
    "selfpaced": true, 
    "topic_name": [
        "Development"
    ], 
    "description": "<p>  \t  A Certificate of Completion will be provided to all students after completing this course.  </p>  <p>  \t<strong style=\"\">HTML5 is a core technology markup language of the Internet used for structuring and presenting content for the World wide web. It is the fifth revision of the HTML standard .</strong>  </p>  <p>  \t<strong style=\"\">&quot;Learn HTML-5 Programming In Just 1 Hour&quot; will make you Learn HTML programming and also you can apply them to make different codes and game development software .</strong>  </p>  <p>  \t  ______________________________________________________________________  </p>  <p>  \t  This course will teach you the full basic knowledge of HTML-5 and techniques of coding in HTML and by the end of this course you will be able to create your program and games in the way you want.  </p>  <p>  \t<span>You&#039;ve always wanted to make your own games. Don&#039;t keep on postponing it. Start TODAY with HTML5 game development for iOS, Android, Amazon and Windows 8</span>  </p>  <p>  \t<strong style=\"\">The Course contains :</strong>  </p>  <p>  \t  1. Videos with complete explaination and clearity.  </p>  <p>  \t  2 . Presentations .  </p>  <p>  \t  3. Complete support on every problem  </p>  <p>  \t  .  </p>  <p>  \t<strong style=\"\">Section included in this course :</strong>  </p>  <p>  \t  1. Let&#039;s start with HTML-5.  </p>  <p>  \t  2. Constructing Shapes in HTML-5.  </p>  <p>  \t  3. Adding Special tags in HTML-5.  </p>  <p>  \t  4. Creating games in HTML-5.  </p>  <p>  \t  5. Using small tags in HTML-5.  </p>  <p>  \t  6. Adding tables in HTML-5.  </p>  <p>  \t  Why only HTML-5 :  </p>  <p>  \t<strong style=\"\">After completing this course you will be able to:</strong>  </p>  <p>  \t  1. Master in programming codes and games.  </p>  <p>  \t  2. Design your program in the way you want.  </p>  <p>  \t  3. Make many new games in the way you want.  </p>", 
    "end_date": null, 
    "title": "HTML5 - Mobile Game Development for Beginners", 
    "price": "20.00", 
    "instructors": "Saksham Jainani", 
    "commitment": "1 hour", 
    "cover_url": "https://udemy-images.udemy.com/course/750x422/413737_b6ea_4.jpg", 
    "course_url": "https://www.udemy.com/html5-mobile-game-development-for-beginners/", 
    "currency": "USD", 
    "subject_name": [
        "Web Development"
    ], 
    "duration": null, 
    "language_name": [
        "English"
    ], 
    "provider_name": [
        "udemy"
    ], 
    "start_date": "2015-02-05T02:33:37Z"
}