{
    "selfpaced": true, 
    "topic_name": [
        "Design"
    ], 
    "description": "<p><strong>Would you like to learn to draw in a few simple, fun, steps with these online drawing class?</strong></p>\r\n<p>Drawing With Confidence is the full and complete course to taking you by the hand through <strong>fun and simple drawing class</strong>. These lessons are for all ages and all levels, from <strong>beginner</strong> all the way up to professional.</p>\r\n<p>Each technique is tried and true as you&#039;ll enjoy seeing each live demonstration create beautiful art work right before your eyes. The drawing course is tought by a world class portrait artist who has completed portraits of people including:&nbsp;</p>\r\n<ul>\r\n<li>The Prince of Dubai</li>\r\n<li>Rupert Murdoch</li>\r\n<li>Ridley Scott</li>\r\n<li>Jeff Skol</li>\r\n</ul>\r\n<p>As well as tought at presitgous art universities and exhibited across the states in notable galleries. He is also the founder of Drawing With Confidence, a complete set of the world&#039;s best art training courses available.</p><p>We hope you will enjoy our drawing lessons,&nbsp;<span>have a great time and happy art making!</span></p>\r\n<p>Sincerely,&nbsp;</p>\r\n<p>~DWC</p>\r\n", 
    "end_date": null, 
    "title": "Drawing With Confidence", 
    "price": "25.00", 
    "instructors": "Evan Peelle", 
    "commitment": "2 hours", 
    "cover_url": "https://udemy-images.udemy.com/course/750x422/16689_c9ec_5.jpg", 
    "course_url": "https://www.udemy.com/drawing-with-confidence/", 
    "currency": "USD", 
    "subject_name": [
        "Graphic Design"
    ], 
    "duration": null, 
    "language_name": [
        "English"
    ], 
    "provider_name": [
        "udemy"
    ], 
    "start_date": "2012-04-21T20:54:54Z"
}