{
    "selfpaced": true, 
    "topic_name": [
        "Design"
    ], 
    "description": "<p>  \t  En  este curso crearemos y veremos la diferencia de hacer cáusticas con los motores de render mental ray y Vray en una piscina.  </p>  <p>  \t  3dsMax es un programa de creación de gráficos y animación 3D desarrollado por Autodesk, en concreto la división Autodesk Media &amp; Entertainment (anteriormente Discreet). Creado inicialmente por el Grupo Yost para Autodesk, salió a la venta por primera vez en 1990 para DOS. 3ds Max, con su arquitectura basada en plugins, es uno de los programas de animación 3D más utilizado, especialmente para la creación de video juegos, anuncios de televisión, en arquitectura o en películas. <br>  \t<br>  \t  Este curso es impartido por Enrique Pesqueira , diseñador gráfico 3D con un master en infoarquitectura hiperrealista. Ha trabajado como infografista y delineante proyectista durante los últimos 5 años en distintos estudios de arquitectura y en 2013 obtuvo el 3Dmax certificate.  </p>", 
    "end_date": null, 
    "title": "Cáusticas en piscina con 3ds Max y Vray", 
    "price": "20.00", 
    "instructors": "Trazos_TV Videoformación online especializada en diseño digital", 
    "commitment": "1 hour", 
    "cover_url": "https://udemy-images.udemy.com/course/750x422/184278_3257.jpg", 
    "course_url": "https://www.udemy.com/causticas-en-piscina-con-3ds-max-y-vray/", 
    "currency": "USD", 
    "subject_name": [
        "3D & Animation"
    ], 
    "duration": null, 
    "language_name": [
        "Others"
    ], 
    "provider_name": [
        "udemy"
    ], 
    "start_date": "2014-03-17T22:45:51Z"
}