{
    "selfpaced": true, 
    "topic_name": [
        "Marketing"
    ], 
    "description": "<p><strong>Vamos Tornar a sua empresa mais interativa nas Redes Sociais!</strong><br></p><p>Neste curso você irá aprender em menos de 2(duas) horas como criar um vídeo animado, economizando dinheiro que você gastaria contratando uma empresa ou profissional da área e o melhor de tudo que você não precisa de conhecimentos avançados para iniciar, precisa apenas de conhecimentos básicos de informática.</p><p><strong>Tempo para você ser capaz de dominar toda a ferramenta:</strong></p><p>2 Horas</p><p><strong>Alguns tópicos abordados:</strong></p><p>- Criação de conta<strong>.</strong></p><p>- Utilização de templates e themas oferecidos pela ferramenta.</p><p>- Alteração de objetos do cenário.</p><p>- Customização de personagens.</p><p>- Alteração de músicas de fundo.</p><p>- Criação de diálogos entre personagens.</p><p>- Efeitos de câmera.</p><p>- Animações de entrada.</p><p>- Transições entre as apresentações e muito mais!</p><p><strong>O que poderei fazer depois do curso?</strong></p><p>Criar um vídeo animado de sua empresa divulgando produtos e serviços, economizando tanto no tempo de aprendizado como no dinheiro , uma vez que você não precisará contratar uma empresa especializada para fazer o serviço.</p><p><br></p><p><br></p><p><br></p><p><br></p>", 
    "end_date": null, 
    "title": "Crie Vídeos Promocionais Animados com GoAnimate!", 
    "price": 0, 
    "instructors": "Elton Oliveira", 
    "commitment": "2 hours", 
    "cover_url": "https://udemy-images.udemy.com/course/750x422/685588_231a_2.jpg", 
    "course_url": "https://www.udemy.com/videos-promocionais-animados/", 
    "subject_name": [
        "Video & Mobile Marketing"
    ], 
    "duration": null, 
    "language_name": [
        "Others"
    ], 
    "provider_name": [
        "udemy"
    ], 
    "start_date": "2015-12-01T01:34:40Z"
}