{
    "selfpaced": true, 
    "topic_name": [
        "Business"
    ], 
    "description": "<p>With growing volatility in business environment, software development process has to be responsive enough to ensure that it enables the business agility rather than becoming a bottle neck. The fast adaption of agile based processes shows that software development groups are responding to the need of business. Most of the recent surveys show growing adaption of Kanban processes and in this program you will learn how to apply Kanban for solving your software development problems.</p><p>This program not only introduces the kanban and lean software development development but provide detailed insight to implement kanban practices for improving your development process. This program gets into the details of kanban principles and see how they can be applied to software development process. The program provide implementable tips for planning and monitoring software development work using kanban. </p><p><strong>This program is approved for 4 Category A PDUs from PMI and 4 Category B SEUs from Scrum Alliance.</strong></p><p>Happy Learning!</p><p>To access the additional material on Project Management and agile like chapter study guides, additional chapter test, simulated test, Podcast, PMP exam tips, please visit iZenBridge homepage.</p>", 
    "end_date": null, 
    "title": "Kanban for Software Development Teams", 
    "price": "50.00", 
    "instructors": "iZenBridge Consultancy", 
    "commitment": "3.5 hours", 
    "cover_url": "https://udemy-images.udemy.com/course/750x422/580778_ee55.jpg", 
    "course_url": "https://www.udemy.com/kanban-for-software-development-teams-izenbridge/", 
    "currency": "USD", 
    "subject_name": [
        "Project Management"
    ], 
    "duration": null, 
    "language_name": [
        "English"
    ], 
    "provider_name": [
        "udemy"
    ], 
    "start_date": "2015-08-12T02:54:28Z"
}