{"selfpaced": true, "topic_name": ["Entrepreneurship"], "description": "\n\n                    \n                    \n                    SOCIAL ENTREPRENEURSHIP \u2013 The use of innovation to find new ways to help people in needPURPOSE OF THIS COURSE:\u00a0This course provides step-by-step instructions for starting small, local, grassroots projects to help selected categories of people in need. Students select a category of people about whom they care, learn details about social entrepreneurship projects, and on paper build a project of their own.THE HOMELESSABANDONED CHILDRENFEEBLE ELDERLYTHE ADDICTEDTEENS CONSIDERING SUICIDE\u2026Hundreds of other categories of people in need\n\n                                            Syllabus\n                        This five week course provides -\r\n1) 16 video presentations by Dr. Campbell discussing core social entrepreneurship issues. In addition, students have\r\n2) reading assignments on the Internet and\r\n3) a writing assignment as they build their social entrepreneurship project.\r\n4) Students pose questions any time, and Dr. Campbell selects the best questions and responds to several questions each working day.\r\n5) There are two quizzes, and a digital badge is received upon completion of the course.\u00a0\n                                    ", "end_date": "2014-04-30T00:00:00Z", "title": "Social Entrepreneurship: A Grassroots Revolution", "price": 0, "instructors": "Keith Campbell", "institution_name": ["Fort Hays State University"], "commitment": "", "subject_name": ["Business & Management"], "course_url": "https://openeducation.blackboard.com/mooc-catalog/courseDetails/view?course_id=_91_1", "duration": "5 weeks", "language_name": ["English"], "provider_name": ["Open Education by Blackboard"], "start_date": "2014-03-26T00:00:00Z"}