{
    "selfpaced": true, 
    "topic_name": [
        "Business"
    ], 
    "description": "<p style=\"\">  \t<span style=\"\">Wouldn’t it be great if learning basic cash &amp; receivables accounting was fast and easy?</span>  </p>  <p style=\"\">  \tThat’s what this course is all about. This course offers students, business owners, and bookkeepers resources that help you master basic cash &amp; receivables accounting. The course offers bite-sized video lessons along with a course handout. Color-coded visuals, simple illustrations, and step-by-step walkthroughs help you master the concepts quickly and easily.  </p>  <p style=\"\">  \tPlease feel free to post a comment or question, and I’ll be happy to respond. Hope you enjoy the course!  </p>  <p style=\"\">  \tLogan Musil  </p>  <p style=\"\">  \t<strong style=\"\">At the end of the course, you will be able to…</strong>  </p>  <p style=\"\">  \tUnderstand the purpose of accounting for cash  </p>  <p style=\"\">  \tUnderstand instruments defined as cash  </p>  <p style=\"\">  \tUnderstand where cash is reported in the financial statements  </p>  <p style=\"\">  \tPrepare a bank reconciliation<strong style=\"\"></strong>  </p>  <p style=\"\">  \tDescribe accounts receivable  </p>  <p style=\"\">  \tDescribe Bad Debt Expense  </p>  <p style=\"\">  \tDescribe Customer account write-off  </p>  <p style=\"\">  \tAccount for accounts receivable upon sales of goods &amp; services  </p>  <p style=\"\">  \tDescribe where receivables are reported in the financial statements  </p>  <p style=\"\">  \tAccount for uncollectible accounts using the Direct Write-off Method  </p>  <p style=\"\">  \tAccount for uncollectible accounts using the Allowance Method  </p>  <p style=\"\">  \tUnderstand the allowance method equation for net realizable value  </p>  <p style=\"\">  \tCalculate estimated uncollectible accounts using the Percentage of Sales Method  </p>  <p style=\"\">  \tCalculate estimated uncollectible accounts using the Aging Method  </p>  <p style=\"\">  \tRecord the write off of uncollectible accounts using the allowance method  </p>", 
    "end_date": null, 
    "title": "Learn Basic Cash & Receivables Accounting – Fast & Easy!", 
    "price": 0, 
    "instructors": "Logan Musil", 
    "commitment": "32 mins", 
    "cover_url": "https://udemy-images.udemy.com/course/750x422/374234_2014_4.jpg", 
    "course_url": "https://www.udemy.com/learn-basic-cash-receivables-accounting-fast-easy/", 
    "subject_name": [
        "Finance"
    ], 
    "duration": null, 
    "language_name": [
        "English"
    ], 
    "provider_name": [
        "udemy"
    ], 
    "start_date": "2014-12-20T01:00:20Z"
}